<?xml version="1.0" encoding="utf-8" ?><dwsync><file name=".DS_Store" server="iis602.ixwebhosting.com/ideasendesarrollo.com/weezlabs/sixgill/" local="3543300937" remote="3543304860" Dst="-1" /><file name="avatar.jpg" server="iis602.ixwebhosting.com/ideasendesarrollo.com/weezlabs/sixgill/" local="3491545364" remote="3543304860" Dst="-1" /><file name="close.png" server="iis602.ixwebhosting.com/ideasendesarrollo.com/weezlabs/sixgill/" local="3501466080" remote="3543304860" Dst="-1" /><file name="dotted.png" server="iis602.ixwebhosting.com/ideasendesarrollo.com/weezlabs/sixgill/" local="3493622656" remote="3543304860" Dst="-1" /><file name="iconalt.svg" server="iis602.ixwebhosting.com/ideasendesarrollo.com/weezlabs/sixgill/" local="3477463044" remote="3543304860" Dst="-1" /><file name="image.png" server="iis602.ixwebhosting.com/ideasendesarrollo.com/weezlabs/sixgill/" local="3493622658" remote="3543304860" Dst="-1" /><file name="mainsubmenuh.png" server="iis602.ixwebhosting.com/ideasendesarrollo.com/weezlabs/sixgill/" local="3493622658" remote="3543304860" Dst="-1" /><file name="mainsubmenu.png" server="iis602.ixwebhosting.com/ideasendesarrollo.com/weezlabs/sixgill/" local="3493622658" remote="3543304860" Dst="-1" /><file name="map-icon-red.png" server="iis602.ixwebhosting.com/ideasendesarrollo.com/weezlabs/sixgill/" local="3493622660" remote="3543304860" Dst="-1" /><file name="map-icon.png" server="iis602.ixwebhosting.com/ideasendesarrollo.com/weezlabs/sixgill/" local="3493622658" remote="3543304860" Dst="-1" /><file name="menu-divider.png" server="iis602.ixwebhosting.com/ideasendesarrollo.com/weezlabs/sixgill/" local="3493622658" remote="3543304860" Dst="-1" /><file name="menu-dividerd.png" server="iis602.ixwebhosting.com/ideasendesarrollo.com/weezlabs/sixgill/" local="3493622660" remote="3543304860" Dst="-1" /><file name="play.png" server="iis602.ixwebhosting.com/ideasendesarrollo.com/weezlabs/sixgill/" local="3493622660" remote="3543304860" Dst="-1" /><file name="submenu-dark.png" server="iis602.ixwebhosting.com/ideasendesarrollo.com/weezlabs/sixgill/" local="3494489514" remote="3543304860" Dst="-1" /><file name="video-play.png" server="iis602.ixwebhosting.com/ideasendesarrollo.com/weezlabs/sixgill/" local="3496385486" remote="3543304860" Dst="-1" /><file name="submenu.png" server="iis602.ixwebhosting.com/ideasendesarrollo.com/weezlabs/sixgill/" local="3493622664" remote="3543304860" Dst="-1" /><file name="widget-link-dark.png" server="iis602.ixwebhosting.com/ideasendesarrollo.com/weezlabs/sixgill/" local="3493699922" remote="3543304860" Dst="-1" /><file name="widget-link-dark@2x.png" server="iis602.ixwebhosting.com/ideasendesarrollo.com/weezlabs/sixgill/" local="3493700134" remote="3543304860" Dst="-1" /><file name="widget-link.png" server="iis602.ixwebhosting.com/ideasendesarrollo.com/weezlabs/sixgill/" local="3493700122" remote="3543304860" Dst="-1" /><file name="widget-link@2x.png" server="iis602.ixwebhosting.com/ideasendesarrollo.com/weezlabs/sixgill/" local="3493700116" remote="3543304860" Dst="-1" /></dwsync>